[
  {
    "type": "move",
    "x": 3154,
    "y": 2258,
    "z": 6
  },
  {
    "type": "move",
    "x": 3154,
    "y": 2259,
    "z": 6
  },
  {
    "type": "move",
    "x": 3154,
    "y": 2260,
    "z": 6
  },
  {
    "type": "move",
    "x": 3154,
    "y": 2261,
    "z": 6
  },
  {
    "type": "move",
    "x": 3154,
    "y": 2262,
    "z": 6
  },
  {
    "type": "move",
    "x": 3154,
    "y": 2263,
    "z": 6
  },
  {
    "type": "move",
    "x": 3154,
    "y": 2264,
    "z": 6
  },
  {
    "type": "move",
    "x": 3155,
    "y": 2264,
    "z": 6
  },
  {
    "type": "move",
    "x": 3156,
    "y": 2264,
    "z": 6
  },
  {
    "type": "move",
    "x": 3157,
    "y": 2264,
    "z": 6
  },
  {
    "type": "move",
    "x": 3159,
    "y": 2264,
    "z": 6
  },
  {
    "type": "move",
    "x": 3160,
    "y": 2264,
    "z": 6
  },
  {
    "type": "move",
    "x": 3160,
    "y": 2263,
    "z": 6
  },
  {
    "type": "move",
    "x": 3160,
    "y": 2262,
    "z": 6
  },
  {
    "type": "move",
    "x": 3160,
    "y": 2261,
    "z": 6
  },
  {
    "type": "move",
    "x": 3160,
    "y": 2260,
    "z": 6
  },
  {
    "type": "move",
    "x": 3160,
    "y": 2259,
    "z": 6
  },
  {
    "type": "move",
    "x": 3160,
    "y": 2258,
    "z": 6
  },
  {
    "type": "move",
    "x": 3159,
    "y": 2258,
    "z": 6
  },
  {
    "type": "move",
    "x": 3158,
    "y": 2258,
    "z": 6
  },
  {
    "type": "move",
    "x": 3157,
    "y": 2258,
    "z": 6
  },
  {
    "type": "move",
    "x": 3156,
    "y": 2258,
    "z": 6
  },
  {
    "type": "move",
    "x": 3154,
    "y": 2258,
    "z": 6
  }
]